{ 
    "1" : { 
        "ID" : 1,
        "X1" : 0,
        "X2" : 0,
        "X3" : 0,
        "X4" : 0,
        "X5" : 0,
        "X6" : 0,
        "X7" : 0,
        "X8" : 0,
        "X9" : 0,
        "X10" : 0,
        "X11" : 0,
        "X12" : 0,
        "X13" : 0,
        "X14" : 0,
        "X15" : 0,
        "X16" : 0,
        "X17" : 0
    },
    "2" : { 
        "ID" : 2,
        "X1" : 0,
        "X2" : 0,
        "X3" : 0,
        "X4" : 0,
        "X5" : 0,
        "X6" : 0,
        "X7" : 0,
        "X8" : 0,
        "X9" : 0,
        "X10" : 0,
        "X11" : 0,
        "X12" : 0,
        "X13" : 0,
        "X14" : 0,
        "X15" : 0,
        "X16" : 0,
        "X17" : 0
    },
    "3" : { 
        "ID" : 3,
        "X1" : 0,
        "X2" : 1,
        "X3" : 1,
        "X4" : 0,
        "X5" : 0,
        "X6" : 0,
        "X7" : 0,
        "X8" : 0,
        "X9" : 0,
        "X10" : 0,
        "X11" : 0,
        "X12" : 0,
        "X13" : 0,
        "X14" : 0,
        "X15" : 0,
        "X16" : 0,
        "X17" : 0
    },
    "4" : { 
        "ID" : 4,
        "X1" : 0,
        "X2" : 1,
        "X3" : 1,
        "X4" : 0,
        "X5" : 0,
        "X6" : 0,
        "X7" : 0,
        "X8" : 0,
        "X9" : 0,
        "X10" : 0,
        "X11" : 0,
        "X12" : 0,
        "X13" : 0,
        "X14" : 0,
        "X15" : 0,
        "X16" : 1,
        "X17" : 1
    },
    "5" : { 
        "ID" : 5,
        "X1" : 0,
        "X2" : 0,
        "X3" : 0,
        "X4" : 0,
        "X5" : 0,
        "X6" : 0,
        "X7" : 0,
        "X8" : 0,
        "X9" : 0,
        "X10" : 0,
        "X11" : 0,
        "X12" : 0,
        "X13" : 0,
        "X14" : 0,
        "X15" : 0,
        "X16" : 1,
        "X17" : 1
    },
    "6" : { 
        "ID" : 6,
        "X1" : 0,
        "X2" : 0,
        "X3" : 0,
        "X4" : 0,
        "X5" : 0,
        "X6" : 0,
        "X7" : 0,
        "X8" : 0,
        "X9" : 0,
        "X10" : 0,
        "X11" : 0,
        "X12" : 0,
        "X13" : 0,
        "X14" : 0,
        "X15" : 0,
        "X16" : 0,
        "X17" : 0
    },
    "7" : { 
        "ID" : 7,
        "X1" : 11,
        "X2" : 0,
        "X3" : 0,
        "X4" : 0,
        "X5" : 0,
        "X6" : 0,
        "X7" : 0,
        "X8" : 0,
        "X9" : 0,
        "X10" : 0,
        "X11" : 0,
        "X12" : 0,
        "X13" : 0,
        "X14" : 0,
        "X15" : 0,
        "X16" : 0,
        "X17" : 0
    },
    "8" : { 
        "ID" : 8,
        "X1" : 0,
        "X2" : 0,
        "X3" : 0,
        "X4" : 0,
        "X5" : 1,
        "X6" : 1,
        "X7" : 1,
        "X8" : 0,
        "X9" : 0,
        "X10" : 0,
        "X11" : 1,
        "X12" : 1,
        "X13" : 1,
        "X14" : 0,
        "X15" : 0,
        "X16" : 0,
        "X17" : 0
    },
    "9" : { 
        "ID" : 9,
        "X1" : 1,
        "X2" : 1,
        "X3" : 0,
        "X4" : 0,
        "X5" : 2,
        "X6" : 2,
        "X7" : 1,
        "X8" : 0,
        "X9" : 0,
        "X10" : 0,
        "X11" : 1,
        "X12" : 2,
        "X13" : 2,
        "X14" : 0,
        "X15" : 0,
        "X16" : 1,
        "X17" : 1
    },
    "10" : { 
        "ID" : 10,
        "X1" : 2,
        "X2" : 2,
        "X3" : 0,
        "X4" : 0,
        "X5" : 2,
        "X6" : 2,
        "X7" : 1,
        "X8" : 0,
        "X9" : 0,
        "X10" : 0,
        "X11" : 1,
        "X12" : 2,
        "X13" : 2,
        "X14" : 0,
        "X15" : 0,
        "X16" : 2,
        "X17" : 2
    },
    "11" : { 
        "ID" : 11,
        "X1" : 1,
        "X2" : 1,
        "X3" : 1,
        "X4" : 1,
        "X5" : 1,
        "X6" : 1,
        "X7" : 1,
        "X8" : 1,
        "X9" : 1,
        "X10" : 1,
        "X11" : 1,
        "X12" : 1,
        "X13" : 1,
        "X14" : 1,
        "X15" : 1,
        "X16" : 1,
        "X17" : 1
    },
    "12" : { 
        "ID" : 12,
        "X1" : 1,
        "X2" : 0,
        "X3" : 0,
        "X4" : 0,
        "X5" : 0,
        "X6" : 0,
        "X7" : 0,
        "X8" : 0,
        "X9" : 0,
        "X10" : 0,
        "X11" : 0,
        "X12" : 0,
        "X13" : 0,
        "X14" : 0,
        "X15" : 0,
        "X16" : 0,
        "X17" : 1
    },
    "13" : { 
        "ID" : 13,
        "X1" : 1,
        "X2" : 0,
        "X3" : 0,
        "X4" : 0,
        "X5" : 0,
        "X6" : 0,
        "X7" : 0,
        "X8" : 0,
        "X9" : 0,
        "X10" : 0,
        "X11" : 0,
        "X12" : 11,
        "X13" : 0,
        "X14" : 0,
        "X15" : 0,
        "X16" : 0,
        "X17" : 1
    },
    "14" : { 
        "ID" : 14,
        "X1" : 1,
        "X2" : 0,
        "X3" : 13,
        "X4" : 2,
        "X5" : 2,
        "X6" : 2,
        "X7" : 0,
        "X8" : 0,
        "X9" : 0,
        "X10" : 0,
        "X11" : 2,
        "X12" : 2,
        "X13" : 2,
        "X14" : 2,
        "X15" : 12,
        "X16" : 0,
        "X17" : 1
    },
    "15" : { 
        "ID" : 15,
        "X1" : 1,
        "X2" : 0,
        "X3" : 0,
        "X4" : 2,
        "X5" : 1,
        "X6" : 1,
        "X7" : 1,
        "X8" : 1,
        "X9" : 1,
        "X10" : 1,
        "X11" : 1,
        "X12" : 1,
        "X13" : 1,
        "X14" : 2,
        "X15" : 0,
        "X16" : 0,
        "X17" : 1
    },
    "16" : { 
        "ID" : 16,
        "X1" : 1,
        "X2" : 0,
        "X3" : 0,
        "X4" : 2,
        "X5" : 1,
        "X6" : 1,
        "X7" : 1,
        "X8" : 1,
        "X9" : 1,
        "X10" : 1,
        "X11" : 1,
        "X12" : 1,
        "X13" : 1,
        "X14" : 0,
        "X15" : 0,
        "X16" : 0,
        "X17" : 1
    },
    "17" : { 
        "ID" : 17,
        "X1" : 1,
        "X2" : 0,
        "X3" : 0,
        "X4" : 2,
        "X5" : 1,
        "X6" : 1,
        "X7" : 1,
        "X8" : 1,
        "X9" : 1,
        "X10" : 3,
        "X11" : 3,
        "X12" : 1,
        "X13" : 1,
        "X14" : 0,
        "X15" : 0,
        "X16" : 0,
        "X17" : 1
    },
    "18" : { 
        "ID" : 18,
        "X1" : 0,
        "X2" : 0,
        "X3" : 11,
        "X4" : 2,
        "X5" : 1,
        "X6" : 1,
        "X7" : 1,
        "X8" : 1,
        "X9" : 1,
        "X10" : 1,
        "X11" : 1,
        "X12" : 1,
        "X13" : 1,
        "X14" : 0,
        "X15" : 0,
        "X16" : 0,
        "X17" : 0
    },
    "19" : { 
        "ID" : 19,
        "X1" : 0,
        "X2" : 0,
        "X3" : 0,
        "X4" : 2,
        "X5" : 1,
        "X6" : 1,
        "X7" : 1,
        "X8" : 1,
        "X9" : 1,
        "X10" : 1,
        "X11" : 1,
        "X12" : 1,
        "X13" : 1,
        "X14" : 2,
        "X15" : 0,
        "X16" : 0,
        "X17" : 0
    },
    "20" : { 
        "ID" : 20,
        "X1" : 0,
        "X2" : 0,
        "X3" : 0,
        "X4" : 0,
        "X5" : 1,
        "X6" : 1,
        "X7" : 1,
        "X8" : 1,
        "X9" : 1,
        "X10" : 1,
        "X11" : 1,
        "X12" : 1,
        "X13" : 1,
        "X14" : 2,
        "X15" : 0,
        "X16" : 0,
        "X17" : 0
    },
    "21" : { 
        "ID" : 21,
        "X1" : 1,
        "X2" : 0,
        "X3" : 0,
        "X4" : 0,
        "X5" : 1,
        "X6" : 1,
        "X7" : 3,
        "X8" : 3,
        "X9" : 1,
        "X10" : 1,
        "X11" : 1,
        "X12" : 1,
        "X13" : 1,
        "X14" : 2,
        "X15" : 0,
        "X16" : 0,
        "X17" : 1
    },
    "22" : { 
        "ID" : 22,
        "X1" : 1,
        "X2" : 0,
        "X3" : 0,
        "X4" : 0,
        "X5" : 1,
        "X6" : 1,
        "X7" : 1,
        "X8" : 1,
        "X9" : 1,
        "X10" : 1,
        "X11" : 1,
        "X12" : 1,
        "X13" : 1,
        "X14" : 2,
        "X15" : 11,
        "X16" : 0,
        "X17" : 1
    },
    "23" : { 
        "ID" : 23,
        "X1" : 1,
        "X2" : 0,
        "X3" : 0,
        "X4" : 2,
        "X5" : 1,
        "X6" : 1,
        "X7" : 1,
        "X8" : 1,
        "X9" : 1,
        "X10" : 1,
        "X11" : 1,
        "X12" : 1,
        "X13" : 1,
        "X14" : 2,
        "X15" : 0,
        "X16" : 0,
        "X17" : 1
    },
    "24" : { 
        "ID" : 24,
        "X1" : 1,
        "X2" : 0,
        "X3" : 12,
        "X4" : 2,
        "X5" : 2,
        "X6" : 2,
        "X7" : 2,
        "X8" : 0,
        "X9" : 0,
        "X10" : 0,
        "X11" : 0,
        "X12" : 2,
        "X13" : 2,
        "X14" : 2,
        "X15" : 13,
        "X16" : 0,
        "X17" : 1
    },
    "25" : { 
        "ID" : 25,
        "X1" : 1,
        "X2" : 0,
        "X3" : 0,
        "X4" : 11,
        "X5" : 0,
        "X6" : 0,
        "X7" : 0,
        "X8" : 0,
        "X9" : 0,
        "X10" : 0,
        "X11" : 0,
        "X12" : 0,
        "X13" : 0,
        "X14" : 0,
        "X15" : 0,
        "X16" : 0,
        "X17" : 1
    },
    "26" : { 
        "ID" : 26,
        "X1" : 1,
        "X2" : 0,
        "X3" : 0,
        "X4" : 0,
        "X5" : 0,
        "X6" : 0,
        "X7" : 0,
        "X8" : 0,
        "X9" : 0,
        "X10" : 0,
        "X11" : 0,
        "X12" : 0,
        "X13" : 0,
        "X14" : 0,
        "X15" : 0,
        "X16" : 0,
        "X17" : 1
    },
    "27" : { 
        "ID" : 27,
        "X1" : 1,
        "X2" : 1,
        "X3" : 1,
        "X4" : 1,
        "X5" : 1,
        "X6" : 1,
        "X7" : 1,
        "X8" : 1,
        "X9" : 1,
        "X10" : 1,
        "X11" : 1,
        "X12" : 1,
        "X13" : 1,
        "X14" : 1,
        "X15" : 1,
        "X16" : 1,
        "X17" : 1
    },
    "28" : { 
        "ID" : 28,
        "X1" : 2,
        "X2" : 2,
        "X3" : 0,
        "X4" : 0,
        "X5" : 2,
        "X6" : 2,
        "X7" : 1,
        "X8" : 0,
        "X9" : 0,
        "X10" : 0,
        "X11" : 1,
        "X12" : 2,
        "X13" : 2,
        "X14" : 0,
        "X15" : 0,
        "X16" : 2,
        "X17" : 2
    },
    "29" : { 
        "ID" : 29,
        "X1" : 1,
        "X2" : 1,
        "X3" : 0,
        "X4" : 0,
        "X5" : 2,
        "X6" : 2,
        "X7" : 1,
        "X8" : 0,
        "X9" : 0,
        "X10" : 0,
        "X11" : 1,
        "X12" : 2,
        "X13" : 2,
        "X14" : 0,
        "X15" : 0,
        "X16" : 1,
        "X17" : 1
    },
    "30" : { 
        "ID" : 30,
        "X1" : 0,
        "X2" : 0,
        "X3" : 0,
        "X4" : 0,
        "X5" : 1,
        "X6" : 1,
        "X7" : 1,
        "X8" : 0,
        "X9" : 0,
        "X10" : 0,
        "X11" : 1,
        "X12" : 1,
        "X13" : 1,
        "X14" : 0,
        "X15" : 0,
        "X16" : 0,
        "X17" : 0
    },
    "31" : { 
        "ID" : 31,
        "X1" : 0,
        "X2" : 0,
        "X3" : 0,
        "X4" : 0,
        "X5" : 0,
        "X6" : 0,
        "X7" : 0,
        "X8" : 0,
        "X9" : 0,
        "X10" : 0,
        "X11" : 0,
        "X12" : 0,
        "X13" : 0,
        "X14" : 0,
        "X15" : 0,
        "X16" : 0,
        "X17" : 0
    },
    "32" : { 
        "ID" : 32,
        "X1" : 0,
        "X2" : 2,
        "X3" : 2,
        "X4" : 0,
        "X5" : 0,
        "X6" : 0,
        "X7" : 0,
        "X8" : 0,
        "X9" : 0,
        "X10" : 0,
        "X11" : 0,
        "X12" : 0,
        "X13" : 0,
        "X14" : 0,
        "X15" : 0,
        "X16" : 0,
        "X17" : 11
    },
    "33" : { 
        "ID" : 33,
        "X1" : 0,
        "X2" : 2,
        "X3" : 2,
        "X4" : 0,
        "X5" : 0,
        "X6" : 0,
        "X7" : 0,
        "X8" : 0,
        "X9" : 0,
        "X10" : 0,
        "X11" : 0,
        "X12" : 0,
        "X13" : 0,
        "X14" : 0,
        "X15" : 2,
        "X16" : 2,
        "X17" : 0
    }

}